CHANGES
COPYING
MANIFEST.in
README.md
setup.py
wsgi2cgi/__init__.py
wsgi2cgi.egg-info/PKG-INFO
wsgi2cgi.egg-info/SOURCES.txt
wsgi2cgi.egg-info/dependency_links.txt
wsgi2cgi.egg-info/not-zip-safe
wsgi2cgi.egg-info/top_level.txt