Metadata-Version: 1.0
Name: wsgi2cgi
Version: 0.2
Summary: Run CGI apps under Python WSGI protocol
Home-page: https://github.com/reidrac/wsgi2cgi
Author: Juan J. Martinez
Author-email: jjm@usebox.net
License: MIT
Platform: UNKNOWN
Classifier: Development Status :: 4 - Beta
Classifier: Environment :: Web Environment
Classifier: Intended Audience :: Developers
Classifier: Topic :: Internet :: WWW/HTTP
Classifier: Topic :: Internet :: WWW/HTTP :: Dynamic Content :: CGI Tools/Libraries
Classifier: Programming Language :: Python
Classifier: Operating System :: OS Independent
Classifier: License :: OSI Approved :: MIT License
